regression_model/VERSION
regression_model/__init__.py
regression_model/pipeline.py
regression_model/predict.py
regression_model/train_pipeline.py
regression_model/config/__init__.py
regression_model/config/core.py
regression_model/datasets/__init__.py
regression_model/processing/__init__.py
regression_model/processing/data_manager.py
regression_model/processing/features.py
regression_model/processing/validation.py
regression_model/trained_models/__init__.py
regression_model/trained_models/regression_model_output_v0.0.1.pkl
fftid_regression_model-0.0.2.dist-info/METADATA
fftid_regression_model-0.0.2.dist-info/WHEEL
fftid_regression_model-0.0.2.dist-info/top_level.txt
fftid_regression_model-0.0.2.dist-info/RECORD
